pyEnvMgr/__init__.py
pyEnvMgr/__main__.py
pyEnvMgr/defaults.py
pyEnvMgr/shell.py
pyEnvMgr/tools.py
pyEnvMgr/utils.py
pyEnvMgr/wrapper.py
pyEnvMgr/compatility/__init__.py
pyEnvMgr/compatility/defaults.py
pyEnvMgr/compatility/shell.py
pyEnvMgr/compatility/shutil.py
pyEnvMgr/compatility/subprocess.py
pyEnvMgr/compatility/tempfile.py
pyEnvMgr-0.1.dist-info/LICENSE
pyEnvMgr-0.1.dist-info/METADATA
pyEnvMgr-0.1.dist-info/WHEEL
pyEnvMgr-0.1.dist-info/top_level.txt
pyEnvMgr-0.1.dist-info/RECORD
