Metadata-Version: 2.1
Name: pyEnvMgr
Version: 0.1
Summary: A tool to handle python environments
Home-page: https://github.com/divad1196/pyEnvMgr
Author: Gallay David
Author-email: davidtennis96@hotmail.com
License: UNKNOWN
Platform: UNKNOWN
Classifier: Programming Language :: Python :: 3
Classifier: License :: OSI Approved :: MIT License
Classifier: Operating System :: OS Independent
